Metadata-Version: 2.1
Name: greek-holidays
Version: 1.0.2
Summary: A package to get Greek national holidays.
Home-page: https://github.com/yourusername/greek-holidays-py
Author: Yiannis Mertzanis
Author-email: imertz@protonmail.com
License: MIT
Keywords: greek holidays
License-File: LICENSE
